tad4bj/__init__.py
tad4bj/__main__.py
tad4bj/dbconn.py
tad4bj/dummy.py
tad4bj/handlers.py
tad4bj/pbs.py
tad4bj/schedulers.py
tad4bj/slurm.py
tad4bj/transformers.py
tad4bj-2.0.dist-info/LICENSE
tad4bj-2.0.dist-info/METADATA
tad4bj-2.0.dist-info/WHEEL
tad4bj-2.0.dist-info/entry_points.txt
tad4bj-2.0.dist-info/top_level.txt
tad4bj-2.0.dist-info/RECORD
