Metadata-Version: 2.1
Name: tad4bj
Version: 2.0
Summary: Tabular Annotations of Data for Batch Jobs
Home-page: https://github.com/alexbarcelo/tad4bj
Author: Alex Barcelo
Author-email: alex@betarho.net
Classifier: Development Status :: 4 - Beta
Classifier: Environment :: Console
Classifier: Intended Audience :: Science/Research
Classifier: Intended Audience :: Information Technology
Classifier: License :: OSI Approved :: GNU General Public License v3 (GPLv3)
Classifier: Operating System :: POSIX
Classifier: Programming Language :: Python :: 3
Classifier: Topic :: Database
Classifier: Topic :: Scientific/Engineering :: Information Analysis
Classifier: Topic :: System :: Logging
License-File: LICENSE
Provides-Extra: yaml
Requires-Dist: pyyaml ; extra == 'yaml'
